README.rst
setup.py
lapostesdk/__init__.py
lapostesdk/laposteapi.py
lapostesdk.egg-info/PKG-INFO
lapostesdk.egg-info/SOURCES.txt
lapostesdk.egg-info/dependency_links.txt
lapostesdk.egg-info/requires.txt
lapostesdk.egg-info/top_level.txt
lapostesdk/apis/__init__.py
lapostesdk/apis/apibase.py
lapostesdk/apis/apicontroladresse.py
lapostesdk/apis/apidatanova.py
lapostesdk/apis/apisuivi.py
lapostesdk/entities/__init__.py
lapostesdk/entities/adresse.py
lapostesdk/entities/base.py
lapostesdk/entities/suivi.py