Metadata-Version: 1.1
Name: lapostesdk
Version: 0.1.2
Summary: La Poste SDK
Home-page: https://github.com/geelweb/laposte-python-sdk
Author: Guillaume Luchet
Author-email: guillaume@geelweb.org
License: UNKNOWN
Download-URL: https://github.com/geelweb/laposte-python-sdk/archive/0.1.2.tar.gz
Keywords: api sdk laposte
Platform: UNKNOWN
